bin/__init__.py
bin/cleanup.sh
bin/create-egg.sh
bin/install_locally.py
bin/mcenter_components_setup.py
bin/mlpiper
ml_comp-1.3.2.data/scripts/cleanup.sh
ml_comp-1.3.2.data/scripts/create-egg.sh
ml_comp-1.3.2.data/scripts/mcenter_components_setup.py
ml_comp-1.3.2.data/scripts/mlpiper
parallelm/__init__.py
parallelm/main.py
parallelm/common/__init__.py
parallelm/common/attr_dict.py
parallelm/common/base.py
parallelm/common/bg_actor.py
parallelm/common/buff_to_lines.py
parallelm/common/byte_conv.py
parallelm/common/cached_property.py
parallelm/common/constants.py
parallelm/common/external_model_info.py
parallelm/common/mlcomp_exception.py
parallelm/common/model_connector_constants.py
parallelm/common/model_connector_helper.py
parallelm/common/os_util.py
parallelm/common/process_monitor.py
parallelm/common/singleton.py
parallelm/common/topological_sort.py
parallelm/components/__init__.py
parallelm/components/command_line_parser.py
parallelm/components/component.py
parallelm/components/connectable_component.py
parallelm/components/connectable_external_component.py
parallelm/components/connected_component_info.py
parallelm/components/external_component.py
parallelm/components/parameter.py
parallelm/components/restful_component.py
parallelm/components/spark_context_component.py
parallelm/components/spark_data_component.py
parallelm/components/spark_pipeline_model_helper.py
parallelm/components/spark_session_component.py
parallelm/components/spark_stage_component.py
parallelm/components/restful/__init__.py
parallelm/components/restful/__template__.py
parallelm/components/restful/constants.py
parallelm/components/restful/flask_app_wrapper.py
parallelm/components/restful/flask_custom_json_encoder.py
parallelm/components/restful/flask_route.py
parallelm/components/restful/metric.py
parallelm/components/restful/nginx_broker.py
parallelm/components/restful/nginx_conf_template.py
parallelm/components/restful/util.py
parallelm/components/restful/uwsgi_broker.py
ml_comp-1.3.2.dist-info/METADATA
ml_comp-1.3.2.dist-info/WHEEL
ml_comp-1.3.2.dist-info/entry_points.txt
ml_comp-1.3.2.dist-info/top_level.txt
ml_comp-1.3.2.dist-info/RECORD
