Metadata-Version: 2.1
Name: ml-comp
Version: 1.3.2
Summary: An engine for running component based ML pipelines
Home-page: https://mlpiper.github.io/mlpiper/mlcomp/
Author: ParallelM
Author-email: info@parallelm.com
License: Apache License 2.0
Platform: UNKNOWN
Classifier: Programming Language :: Python :: 2
Classifier: Programming Language :: Python :: 3
Classifier: License :: OSI Approved :: Apache Software License
Classifier: Operating System :: MacOS
Classifier: Operating System :: POSIX
Classifier: Operating System :: Unix
Requires-Python: >=2.7, !=3.0.*, !=3.1.*, !=3.2.*, !=3.3.*
Requires-Dist: ml-ops
Requires-Dist: wheel
Requires-Dist: termcolor
Requires-Dist: flask
Requires-Dist: flask-cors
Requires-Dist: psutil
Requires-Dist: py4j
Requires-Dist: nbformat
Requires-Dist: nbconvert
Requires-Dist: uwsgidecorators
Requires-Dist: sagemaker
Requires-Dist: pypsi
Requires-Dist: pytz
Requires-Dist: future
